{
  "code": "OK",
  "message": "成功",
  "data": {
    "asin": "B0FDQHJ46H",
    "asinUrl": "https://www.amazon.com/dp/B0FDQHJ46H?psc=1",
    "availableDate": 1750176000000,
    "brand": "Midea",
    "brandUrl": "/stores/Makeyourselfathome/page/4F6A19CF-5B7B-4D5A-A739-6EA8B46D4560?lp_asin=B0FDQHJ46H&ref_=ast_bln&store_ref=bl_ast_dp_brandlogo_sto",
    "bsrId": "home-garden",
    "bsrLabel": "Home & Kitchen",
    "bsrRank": 15499,
    "subcategories": [
      {
        "rank": 29,
        "code": "3737721",
        "label": "Window Air Conditioners"
      }
    ],
    "createdTime": null,
    "dimensions": "19.17\"D x 21.97\"W x 13.46\"H",
    "firstRatingDate": 1753545600000,
    "imageUrl": "https://m.media-amazon.com/images/I/41do8LD2UlL._AC_SR200,200_.jpg",
    "lqs": 95,
    "nodeId": 3737721,
    "nodeIdPath": "1055398:3206324011:14554126011:3737721",
    "nodeLabelPath": "Home & Kitchen:Heating, Cooling & Air Quality:Air Conditioners:Window",
    "nodeLabelPathLocale": null,
    "parent": "B0H1SP2TCJ",
    "price": 509.99,
    "primePrice": -1.0,
    "deliveryPrice": -1.0,
    "coupon": "",
    "questions": null,
    "rating": 4.2,
    "ratings": 597,
    "reviews": 295,
    "variantRatings": 0,
    "variantReviews": 335,
    "sellerId": "A2KW85HMPORX8W",
    "sellerName": "Coffee Appliances",
    "fulfillment": "NA",
    "sellers": 7,
    "marketplace": "US",
    "title": "Midea 12,000 BTU U Shaped Smart Inverter Window Air Conditioner - Cools 550 Sq Ft, Ultra Quiet with Open Window Flexibility - Alexa/Google Assistant Compatible - 35% Energy Savings, Remote (Updated)",
    "updatedTime": 1783346146000,
    "variations": 3,
    "weight": "58.86 Pounds",
    "zoomImageUrl": "https://m.media-amazon.com/images/I/41do8LD2UlL._AC_SR600,600_.jpg",
    "skuList": [
      "Style: 12,000 BTU (Updated)"
    ],
    "variationList": [
      {
        "asin": "B0FDQHJ46H",
        "attribute": "Style: 12,000 BTU (Updated)"
      },
      {
        "asin": "B0FDQGPCG7",
        "attribute": "Style: 8,000 BTU (Updated)"
      },
      {
        "asin": "B0FDQLNGHZ",
        "attribute": "Style: 10,000 BTU (Updated)"
      }
    ],
    "features": [
      "ULTRA QUIET - The U-shape design of Midea U Smart Inverter AC uses your window to block noise outside. The highly-efficient inverter system warrants ultra-low noise and vibration, 10x quieter than traditional units with operation as low as 32 dBA.Control Type: Electronic. Clean Filter Indicator Light: Yes. Rated Cooling Amps (AHAM): 12.17. Refrigerant: R32. Cooling Watts: 1140W.",
      "MORE THAN 35% ENERGY SAVINGS - With the advanced DC Inverter technology, Midea U window air conditioner achieves over 35% energy savings compared to other traditional units. It is the first window AC to obtain the ENERGY STAR Certification.",
      "SMART CONTROL - Midea U Smart Inverter AC is Wi-Fi enabled and can be controlled from anywhere using the SmartHome app on iOS or Android. You can also use voice commands throughout your house, office, or apartment using Alexa or Google Assistant devices.",
      "FLEXIBLE WINDOW OPENING - The U-shaped design allows your window to open, bringing fresh air into your home and maintaining more of your view when the unit is installed. When the window is closed, the Anti-Theft Mechanism locks the window for added safety.",
      "ROBUST INSTALLATION - Install the included quick-snap bracket, set the unit on the bracket, and secure the sidearms. Then you are all done and ready to enjoy. Available for single-hung or double-hung windows with width 22\"-36\", minimal height at 13.75\"."
    ],
    "overviews": "{\"Brand\":\"Midea\",\"Capacity\":\"1 tons\",\"Cooling Power\":\"12000 British Thermal Units\",\"Special Feature\":\"Dehumidifier, Dust Filter, Fast Cooling, Remote Controlled\",\"Product Dimensions\":\"19.17\\\"D x 21.97\\\"W x 13.46\\\"H\",\"Start year\":\"2022\",\"Seasonal Energy Efficiency Ratio (SEER)\":\"15\",\"Color\":\"White\",\"Voltage\":\"115 Volts\",\"Noise Level\":\"32 Decibels\"}",
    "badge": {
      "bestSeller": "N",
      "amazonChoice": "N",
      "newRelease": "N",
      "ebc": "Y",
      "video": "Y"
    }
  }
}
