{
  "data": {
    "trends": [
      {
        "week": "2026-04-18",
        "weekly_search_volume": 500000,
        "aba_rank": 50
      },
      {
        "week": "2026-04-25",
        "weekly_search_volume": 505000,
        "aba_rank": 49
      },
      {
        "week": "2026-05-02",
        "weekly_search_volume": 510000,
        "aba_rank": 48
      },
      {
        "week": "2026-05-09",
        "weekly_search_volume": 515000,
        "aba_rank": 47
      },
      {
        "week": "2026-05-16",
        "weekly_search_volume": 520000,
        "aba_rank": 46
      },
      {
        "week": "2026-05-23",
        "weekly_search_volume": 525000,
        "aba_rank": 45
      },
      {
        "week": "2026-05-30",
        "weekly_search_volume": 530000,
        "aba_rank": 44
      },
      {
        "week": "2026-06-06",
        "weekly_search_volume": 535000,
        "aba_rank": 43
      },
      {
        "week": "2026-06-13",
        "weekly_search_volume": 540000,
        "aba_rank": 42
      },
      {
        "week": "2026-06-20",
        "weekly_search_volume": 545000,
        "aba_rank": 41
      },
      {
        "week": "2026-06-27",
        "weekly_search_volume": 550000,
        "aba_rank": 40
      },
      {
        "week": "2026-07-04",
        "weekly_search_volume": 555000,
        "aba_rank": 39
      }
    ]
  }
}